{
"type": "FeatureCollection",
"name": "bus_routes_402_Saturday",
"crs": { "type": "name", "properties": { "name": "urn:ogc:def:crs:OGC:1.3:CRS84" } },
"features": [
{ "type": "Feature", "properties": { "LineDesignation": "402", "Weekday": 6.0 }, "geometry": { "type": "Point", "coordinates": [ 11.785596320310001, 55.438882414033003 ] } },
{ "type": "Feature", "properties": { "LineDesignation": "402", "Weekday": 6.0 }, "geometry": { "type": "Point", "coordinates": [ 11.784015851581, 55.445434514214 ] } },
{ "type": "Feature", "properties": { "LineDesignation": "402", "Weekday": 6.0 }, "geometry": { "type": "Point", "coordinates": [ 11.789829939778, 55.445765403237999 ] } },
{ "type": "Feature", "properties": { "LineDesignation": "402", "Weekday": 6.0 }, "geometry": { "type": "Point", "coordinates": [ 11.794580368266001, 55.445664605121998 ] } },
{ "type": "Feature", "properties": { "LineDesignation": "402", "Weekday": 6.0 }, "geometry": { "type": "Point", "coordinates": [ 11.799669116166999, 55.445330487452999 ] } },
{ "type": "Feature", "properties": { "LineDesignation": "402", "Weekday": 6.0 }, "geometry": { "type": "Point", "coordinates": [ 11.804182880618001, 55.445387520784003 ] } },
{ "type": "Feature", "properties": { "LineDesignation": "402", "Weekday": 6.0 }, "geometry": { "type": "Point", "coordinates": [ 11.809336341552999, 55.445345844915998 ] } },
{ "type": "Feature", "properties": { "LineDesignation": "402", "Weekday": 6.0 }, "geometry": { "type": "Point", "coordinates": [ 11.813284606976, 55.4440469635 ] } },
{ "type": "Feature", "properties": { "LineDesignation": "402", "Weekday": 6.0 }, "geometry": { "type": "Point", "coordinates": [ 11.820221110927999, 55.444584336833003 ] } },
{ "type": "Feature", "properties": { "LineDesignation": "402", "Weekday": 6.0 }, "geometry": { "type": "Point", "coordinates": [ 11.824755514211001, 55.442759282361003 ] } },
{ "type": "Feature", "properties": { "LineDesignation": "402", "Weekday": 6.0 }, "geometry": { "type": "Point", "coordinates": [ 11.819567945738999, 55.441070763306001 ] } },
{ "type": "Feature", "properties": { "LineDesignation": "402", "Weekday": 6.0 }, "geometry": { "type": "Point", "coordinates": [ 11.814069468767, 55.440599041653002 ] } },
{ "type": "Feature", "properties": { "LineDesignation": "402", "Weekday": 6.0 }, "geometry": { "type": "Point", "coordinates": [ 11.812004902885, 55.442447027564 ] } },
{ "type": "Feature", "properties": { "LineDesignation": "402", "Weekday": 6.0 }, "geometry": { "type": "Point", "coordinates": [ 11.809344879931, 55.445387421661998 ] } },
{ "type": "Feature", "properties": { "LineDesignation": "402", "Weekday": 6.0 }, "geometry": { "type": "Point", "coordinates": [ 11.803980183964001, 55.445380520328001 ] } },
{ "type": "Feature", "properties": { "LineDesignation": "402", "Weekday": 6.0 }, "geometry": { "type": "Point", "coordinates": [ 11.799153073694001, 55.445326029176002 ] } },
{ "type": "Feature", "properties": { "LineDesignation": "402", "Weekday": 6.0 }, "geometry": { "type": "Point", "coordinates": [ 11.79367050848, 55.445665053862001 ] } },
{ "type": "Feature", "properties": { "LineDesignation": "402", "Weekday": 6.0 }, "geometry": { "type": "Point", "coordinates": [ 11.787783670624, 55.445838881417998 ] } },
{ "type": "Feature", "properties": { "LineDesignation": "402", "Weekday": 6.0 }, "geometry": { "type": "Point", "coordinates": [ 11.783735358764, 55.445210946831999 ] } },
{ "type": "Feature", "properties": { "LineDesignation": "402", "Weekday": 6.0 }, "geometry": { "type": "Point", "coordinates": [ 11.785596320310001, 55.438882414033003 ] } }
]
}
