{
"type": "FeatureCollection",
"name": "bus_routes_332_Sunday",
"crs": { "type": "name", "properties": { "name": "urn:ogc:def:crs:OGC:1.3:CRS84" } },
"features": [
{ "type": "Feature", "properties": { "LineDesignation": "332", "Weekday": 7.0 }, "geometry": { "type": "Point", "coordinates": [ 12.373663512378, 55.811872564300998 ] } },
{ "type": "Feature", "properties": { "LineDesignation": "332", "Weekday": 7.0 }, "geometry": { "type": "Point", "coordinates": [ 12.375906516562001, 55.813435082947002 ] } },
{ "type": "Feature", "properties": { "LineDesignation": "332", "Weekday": 7.0 }, "geometry": { "type": "Point", "coordinates": [ 12.378534508107, 55.815499912897998 ] } },
{ "type": "Feature", "properties": { "LineDesignation": "332", "Weekday": 7.0 }, "geometry": { "type": "Point", "coordinates": [ 12.386782960250001, 55.815473052988999 ] } },
{ "type": "Feature", "properties": { "LineDesignation": "332", "Weekday": 7.0 }, "geometry": { "type": "Point", "coordinates": [ 12.39387916888, 55.815891805897003 ] } },
{ "type": "Feature", "properties": { "LineDesignation": "332", "Weekday": 7.0 }, "geometry": { "type": "Point", "coordinates": [ 12.396980186235, 55.818572367685 ] } },
{ "type": "Feature", "properties": { "LineDesignation": "332", "Weekday": 7.0 }, "geometry": { "type": "Point", "coordinates": [ 12.394880253287999, 55.821495418217999 ] } },
{ "type": "Feature", "properties": { "LineDesignation": "332", "Weekday": 7.0 }, "geometry": { "type": "Point", "coordinates": [ 12.391838790746, 55.821318643730997 ] } },
{ "type": "Feature", "properties": { "LineDesignation": "332", "Weekday": 7.0 }, "geometry": { "type": "Point", "coordinates": [ 12.387235060505001, 55.820648860413002 ] } },
{ "type": "Feature", "properties": { "LineDesignation": "332", "Weekday": 7.0 }, "geometry": { "type": "Point", "coordinates": [ 12.388066422953999, 55.817308826266 ] } },
{ "type": "Feature", "properties": { "LineDesignation": "332", "Weekday": 7.0 }, "geometry": { "type": "Point", "coordinates": [ 12.386891803977999, 55.815602762216002 ] } },
{ "type": "Feature", "properties": { "LineDesignation": "332", "Weekday": 7.0 }, "geometry": { "type": "Point", "coordinates": [ 12.378064698556001, 55.815602740246 ] } },
{ "type": "Feature", "properties": { "LineDesignation": "332", "Weekday": 7.0 }, "geometry": { "type": "Point", "coordinates": [ 12.375784488249, 55.813849233356002 ] } },
{ "type": "Feature", "properties": { "LineDesignation": "332", "Weekday": 7.0 }, "geometry": { "type": "Point", "coordinates": [ 12.373663512378, 55.811872564300998 ] } }
]
}
